{
  "monday": {
    "date": "06/10",
    "14:30-16:00": ["Andres | Hermeneutics - Season 2"],
    "16:00-17:30": ["Koen | Jacquerie, a communal uprising"],
    "17:30-19:00": ["Will | The Windbridge Experience"]
  },
  "tuesday": {
    "date": "07/10",
    "14:30-16:00": ["Alula"],
    "16:00-17:30": ["Jack"],
    "17:30-19:00": ["jgsleepy"]
  },
  "wednesday": {
    "date": "08/10",
    "14:30-16:00": ["Common Ground"],
    "16:00-17:30": ["Concrete Soapbox"],
    "17:30-19:00": ["Sheps"]
  },
  "thursday": {
    "date": "09/10",
    "14:30-16:00": ["Antonin"],
    "16:00-17:30": ["Jama48"],
    "17:30-19:00": ["Mia"]
  },
  "friday": {
    "date": "10/10",
    "14:30-16:00": ["Riccardo"],
    "16:00-17:30": ["Bruno"],
    "17:30-19:00": ["Ugur"]
  },
  "saturday": {
    "date": "11/10",
    "14:15-16:00": ["SLIM INVITES #16 "]
  }
}
